{"name":"Elips PHP","tagline":"Simple, Fast & Efficient PHP Framework with less configuration","body":"### ELIPS PHP Framework\r\nSimple, Fast &amp; Efficient PHP Framework with less configuration\r\n\r\n### Server Requirements\r\n- PHP version 5.3.0 or newer\r\n- enable mod_rewrite module in apache\r\n\r\n### Authors and Contributors\r\nIn 2015, Joko Purnomo A (@jokopurnomoa).\r\n\r\n### License\r\nThe Elips PHP framework is open-sourced software licensed under the [MIT license](http://opensource.org/licenses/MIT)","google":"","note":"Don't delete this file! It's used internally to help with page regeneration."}